kapow/__init__.py
kapow/appdirs.py
kapow/cli/__init__.py
kapow/cli/commands.py
kapow/cli/project.py
kapow/cli/resources/__init__.py
kapow/cli/resources/argparse_cli.txt
kapow/cli/resources/argparse_commands.txt
kapow/cli/resources/cli.txt
kapow/cli/resources/commands.txt
kapow/cli/resources/init.txt
kapow/confirm.py
kapow/console.py
kapow/errors.py
kapow/handlers/__init__.py
kapow/handlers/argparse/__init__.py
kapow/handlers/core/__init__.py
kapow/handlers/docopt/__init__.py
kapow/handlers/docopt/handlers.py
kapow/resources/__init__.py
kapow/resources/logging.ini
kapow-0.2.2.dist-info/entry_points.txt
kapow-0.2.2.dist-info/WHEEL
kapow-0.2.2.dist-info/METADATA
kapow-0.2.2.dist-info/RECORD
