Metadata-Version: 2.1
Name: kapow
Version: 0.2.2
Summary: 
Home-page: https://github.com/markgemmill/kapow
License: MIT
Author: Mark Gemmill
Author-email: mark@markgemmill.com
Maintainer: Mark Gemmill
Maintainer-email: dev@markgemmill.com
Requires-Python: >=3.9,<4.0
Classifier: Development Status :: 3 - Alpha
Classifier: Intended Audience :: Developers
Classifier: License :: OSI Approved :: MIT License
Classifier: Operating System :: Microsoft :: Windows
Classifier: Operating System :: POSIX
Classifier: Programming Language :: Python :: 3
Classifier: Programming Language :: Python :: 3 :: Only
Classifier: Programming Language :: Python :: 3.10
Classifier: Programming Language :: Python :: 3.11
Classifier: Programming Language :: Python :: 3.6
Classifier: Programming Language :: Python :: 3.7
Classifier: Programming Language :: Python :: 3.8
Classifier: Programming Language :: Python :: 3.9
Classifier: Topic :: Software Development
Classifier: Topic :: Software Development :: Libraries :: Application Frameworks
Requires-Dist: docopt-ng (>=0.7.2,<0.8.0)
Requires-Dist: rich (>=11.2.0,<12.0.0)
Requires-Dist: tomlkit (>=0.9.2,<0.10.0)
Project-URL: Repository, https://github.com/markgemmill/kapow
